Workbook

Sheet CUSTOM  INVOICE
F1: ALPHA START LIMITED
F2: 7/F EGL TOWER,
F3: 83 HUNG TO ROAD, KWUN TONG
F4: KOWLOON, HONG KONG.
F5: TEL: 3512 0800 FAX: 2345 8558
F7: CUSTOMS INVOICE
A9: DATE OF EXPORTATION : | D9: 46280 | H9: SHIPPING MARKS : | J9: ROSE-FOC
J10: DHAKA,BD
A11: CONSIGNEE : | C11: THE ROSE DRESSES LTD
C12: DIAKHALI, YEARPUR
C13: JAMGORA,ASHULIA, SAVAR,
C14: DHAKA-1349, Bangladesh
C15: BIN: 000517241-0403
A20: COUNTRY OF ULTIMATE DESTINATION : | E20: BANGLADESH
A22: CUSTOMS INVOICE NO.: | D22: S/ 5075/26
A25: TOTAL: | B25: 1 | C25: PKG(S) ONLY | E25: GW: | F25: 3 | G25: KGS
E26: NW: | F26: 2.7 | G26: KGS
G28: UNIT | I28: TOTAL
A29: C/NO. | B29: DESCRIPTION OF GOODS | E29: QUANTITY | G29: PRICE | I29: VALUE
G30: USD | I30: USD
A32: 1 | B32: DIE MOULD ( SNAP) | E32: 5 | F32: SETS | G32: 0.7185 | I32: =E32*G32 -> 3.5925
B34: DIE MOULD ( SHANK ) | E34: 5 | F34: SETS | G34: 0.7185 | I34: =E34*G34 -> 3.5925
B36: DIE MOULD ( RIVET ) | E36: 8 | F36: SETS | G36: 0.7185 | I36: =E36*G36 -> 5.748
I39: 13
A43: MOULD
A44: FOR 100% EXPORT ORIENTED GARMENTS INDUSTRY.
A45: Free of cost,Shipment under export sales contract# ROSE-00251 Dated:24-Jun-26

Sheet PACKING LIST
E1: ALPHA START LIMITED
E2: 7/F EGL TOWER,
E3: 83 HUNG TO ROAD, KWUN TONG
E4: KOWLOON, HONG KONG.
E5: TEL: 3512 0800 FAX: 2345 8558
E7: PACKING LIST
A9: DATE OF EXPORTATION : | D9: 46266 | G9: SHIPPING MARKS : | J9: ROSE-FOC
J10: DHAKA,BD
A11: CONSIGNEE : | C11: =+'CUSTOM INVOICE'!C11 -> THE ROSE DRESSES LTD
C12: =+'CUSTOM INVOICE'!C12 -> DIAKHALI, YEARPUR
C13: =+'CUSTOM INVOICE'!C13 -> JAMGORA,ASHULIA, SAVAR,
C14: =+'CUSTOM INVOICE'!C14 -> DHAKA-1349, Bangladesh
C15: =+'CUSTOM INVOICE'!C15 -> BIN: 000517241-0403
A17: AIRWAYBILL NO. | C17: =+'CUSTOM INVOICE'!C17 -> 0 | D17: =+'CUSTOM INVOICE'!D17 -> 0
A20: COUNTRY OF ULTIMATE DESTINATION : | E20: =+'CUSTOM INVOICE'!E20 -> BANGLADESH
A22: CUSTOMS INVOICE NO.: | D22: =+'CUSTOM INVOICE'!D22 -> S/ 5075/26
A25: TOTAL: | B25: =+'CUSTOM INVOICE'!B25 -> 1 | C25: =+'CUSTOM INVOICE'!C25 -> PKG(S) ONLY | E25: =+'CUSTOM INVOICE'!E25 -> GW: | F25: =+'CUSTOM INVOICE'!F25 -> 3 | G25: =+'CUSTOM INVOICE'!G25 -> KGS
E26: =+'CUSTOM INVOICE'!E26 -> NW: | F26: =+'CUSTOM INVOICE'!F26 -> 2.7 | G26: =+'CUSTOM INVOICE'!G26 -> KGS
A29: C/NO. | B29: DESCRIPTION OF GOODS | E29: QUANTITY
A31: 1 | B31: DIE MOULD ( SHANK ) | E31: 2 | F31: SETS
B33: DIE MOULD ( RIVET ) | E33: 6 | F33: SETS
A35: ='CUSTOM INVOICE'!A46
A42: MOULD
A43: =+'CUSTOM INVOICE'!A44 -> FOR 100% EXPORT ORIENTED GARMENTS INDUSTRY.
A44: =+'CUSTOM INVOICE'!A45 -> Free of cost,Shipment under export sales contract# ROSE-00251 Dated:24-Jun-26
